pymysql_kits/__init__.py
pymysql_kits/_connector.py
pymysql_kits/errors.py
pymysql_kits/pooling.py
pymysql_kits-0.1.4.dist-info/LICENSE
pymysql_kits-0.1.4.dist-info/METADATA
pymysql_kits-0.1.4.dist-info/WHEEL
pymysql_kits-0.1.4.dist-info/top_level.txt
pymysql_kits-0.1.4.dist-info/RECORD
