Metadata-Version: 2.1
Name: pymysql-kits
Version: 0.1.4
Summary: pymysql_kits is a tool based on PyMySQL. It can quickly establish a database connection pool and conveniently execute SQL statements.
Home-page: https://github.com/guanzhenxing/pymysql-kits
Author: Jesen Kwan
Author-email: guan.zhenxing@foxmail.com
License: MIT
Keywords: pymysql connection pool
Platform: UNKNOWN
Classifier: Development Status :: 5 - Production/Stable
Classifier: Programming Language :: Python :: 3
Classifier: Programming Language :: Python :: 3.4
Classifier: Programming Language :: Python :: 3.5
Classifier: Programming Language :: Python :: 3.6
Classifier: Programming Language :: Python :: 3.7
Classifier: Programming Language :: Python :: 3.8
Classifier: Programming Language :: Python :: Implementation :: CPython
Classifier: Programming Language :: Python :: Implementation :: PyPy
Classifier: Intended Audience :: Developers
Classifier: License :: OSI Approved :: MIT License
Classifier: Topic :: Database
Requires-Python: >=3.4.0
Requires-Dist: pymysql
